hash_directory/__init__.py
hash_directory/__main__.py
hash_directory/terminal_formatting.py
hash_directory/version.py
hash_directory-2025.10.16.dist-info/METADATA
hash_directory-2025.10.16.dist-info/WHEEL
hash_directory-2025.10.16.dist-info/entry_points.txt
hash_directory-2025.10.16.dist-info/licenses/LICENSE.txt
hash_directory-2025.10.16.dist-info/RECORD
