Metadata-Version: 2.4
Name: hash-directory
Version: 2025.10.16
Summary: A command line program (and python library) for hashing directories. Can also do hash-based comparisons between directories (like diff -qr).
Author-email: Guenthner <guenthner.jonathan@gmail.com>
License-File: LICENSE.txt
Classifier: License :: OSI Approved :: MIT License
Classifier: Operating System :: OS Independent
Classifier: Programming Language :: Python :: 3
Requires-Python: >=3.8
